singlemodeladmin/__init__.py
singlemodeladmin-0.9.dist-info/METADATA
singlemodeladmin-0.9.dist-info/RECORD
singlemodeladmin-0.9.dist-info/WHEEL
singlemodeladmin-0.9.dist-info/top_level.txt
